maimai_ffi/model.cpython-311-darwin.so
maimai_ffi/exceptions.cpython-311-darwin.so
maimai_ffi/arcade.cpython-311-darwin.so
maimai_ffi/request.cpython-311-darwin.so
maimai_ffi-0.6.0.dist-info/RECORD
maimai_ffi-0.6.0.dist-info/WHEEL
maimai_ffi-0.6.0.dist-info/top_level.txt
maimai_ffi-0.6.0.dist-info/METADATA
maimai_ffi-0.6.0.dist-info/licenses/LICENSE
