Metadata-Version: 2.4
Name: maimai_ffi
Version: 0.6.0
Summary: The definitive wahlap implement for maimai.py in Cython.
License-File: LICENSE
Dynamic: license-file
Dynamic: summary
